{
  "regionCode" : "GM0085",
  "numbersDate" : "2021-03-13T01:00:00+01:00",
  "positiveCases" : {
    "new" : 6,
    "trend" : 5,
    "total" : 859,
    "per100KInhabitants" : 23.558050155639648
  },
  "deaths" : {
    "new" : 0,
    "trend" : 0,
    "total" : 6,
    "per100KInhabitants" : 0
  },
  "securityRegionName" : "Fryslân",
  "updatedAt" : "2021-03-13T17:51:03+01:00",
  "hospitalAdmissions" : {
    "new" : 0,
    "trend" : 0,
    "total" : 32,
    "per100KInhabitants" : 0
  },
  "provinceName" : "Fryslân",
  "municupalityName" : "Ooststellingwerf"
}