{
  "regionCode" : "GM0072",
  "numbersDate" : "2022-01-04T01:00:00+01:00",
  "positiveCases" : {
    "new" : 14,
    "trend" : 1,
    "total" : 1885,
    "per100KInhabitants" : 89.047195434570312
  },
  "deaths" : {
    "new" : 0,
    "trend" : 0,
    "total" : 8,
    "per100KInhabitants" : 0
  },
  "securityRegionName" : "Fryslân",
  "updatedAt" : "2022-01-04T15:32:39+01:00",
  "hospitalAdmissions" : {
    "new" : 0,
    "trend" : 0,
    "total" : 43,
    "per100KInhabitants" : 0
  },
  "provinceName" : "Fryslân",
  "municupalityName" : "Harlingen"
}