{
  "regionCode" : "GM0034",
  "numbersDate" : "2022-01-23T01:00:00+01:00",
  "positiveCases" : {
    "new" : 487,
    "trend" : -499,
    "total" : 47859,
    "per100KInhabitants" : 229.83297729492188
  },
  "deaths" : {
    "new" : 0,
    "trend" : 0,
    "total" : 124,
    "per100KInhabitants" : 0
  },
  "securityRegionName" : "Flevoland",
  "updatedAt" : "2022-01-23T19:31:37+01:00",
  "hospitalAdmissions" : {
    "new" : 3,
    "trend" : 0,
    "total" : 743,
    "per100KInhabitants" : 1.4158089160919189
  },
  "provinceName" : "Flevoland",
  "municupalityName" : "Almere"
}