{
  "regionCode" : "GM0109",
  "numbersDate" : "2022-06-27T02:00:00+02:00",
  "positiveCases" : {
    "new" : 3,
    "trend" : -5,
    "total" : 14646,
    "per100KInhabitants" : 8.4993057250976562
  },
  "deaths" : {
    "new" : 0,
    "trend" : 0,
    "total" : 35,
    "per100KInhabitants" : 0
  },
  "securityRegionName" : "Drenthe",
  "updatedAt" : "2022-06-27T16:22:25+02:00",
  "hospitalAdmissions" : {
    "new" : 0,
    "trend" : 0,
    "total" : 212,
    "per100KInhabitants" : 0
  },
  "provinceName" : "Drenthe",
  "municupalityName" : "Coevorden"
}