{
  "regionCode" : "GM0171",
  "numbersDate" : "2022-01-02T01:00:00+01:00",
  "positiveCases" : {
    "new" : 58,
    "trend" : 32,
    "total" : 7865,
    "per100KInhabitants" : 122.64490509033203
  },
  "deaths" : {
    "new" : 0,
    "trend" : 0,
    "total" : 34,
    "per100KInhabitants" : 0
  },
  "securityRegionName" : "Flevoland",
  "updatedAt" : "2022-01-02T17:48:45+01:00",
  "hospitalAdmissions" : {
    "new" : 0,
    "trend" : 0,
    "total" : 130,
    "per100KInhabitants" : 0
  },
  "provinceName" : "Flevoland",
  "municupalityName" : "Noordoostpolder"
}