{
  "regionCode" : "GM0166",
  "numbersDate" : "2021-11-14T01:00:00+01:00",
  "positiveCases" : {
    "new" : 47,
    "trend" : -6,
    "total" : 5855,
    "per100KInhabitants" : 86.525894165039062
  },
  "deaths" : {
    "new" : 0,
    "trend" : -1,
    "total" : 48,
    "per100KInhabitants" : 0
  },
  "securityRegionName" : "IJsselland",
  "updatedAt" : "2021-11-14T15:26:29+01:00",
  "hospitalAdmissions" : {
    "new" : 0,
    "trend" : -1,
    "total" : 104,
    "per100KInhabitants" : 0
  },
  "provinceName" : "Overijssel",
  "municupalityName" : "Kampen"
}