{
  "regionCode" : "GM0148",
  "numbersDate" : "2021-11-01T01:00:00+01:00",
  "positiveCases" : {
    "new" : 3,
    "trend" : -10,
    "total" : 2911,
    "per100KInhabitants" : 10.494279861450195
  },
  "deaths" : {
    "new" : 0,
    "trend" : 0,
    "total" : 22,
    "per100KInhabitants" : 0
  },
  "securityRegionName" : "IJsselland",
  "updatedAt" : "2021-11-01T19:39:30+01:00",
  "hospitalAdmissions" : {
    "new" : 0,
    "trend" : 0,
    "total" : 49,
    "per100KInhabitants" : 0
  },
  "provinceName" : "Overijssel",
  "municupalityName" : "Dalfsen"
}