{
  "regionCode" : "GM0274",
  "numbersDate" : "2021-03-11T01:00:00+01:00",
  "positiveCases" : {
    "new" : 5,
    "trend" : -1,
    "total" : 1448,
    "per100KInhabitants" : 15.913938522338867
  },
  "deaths" : {
    "new" : 0,
    "trend" : 0,
    "total" : 24,
    "per100KInhabitants" : 0
  },
  "securityRegionName" : "Gelderland-Midden",
  "updatedAt" : "2021-03-11T23:37:59+01:00",
  "hospitalAdmissions" : {
    "new" : 0,
    "trend" : 0,
    "total" : 45,
    "per100KInhabitants" : 0
  },
  "provinceName" : "Gelderland",
  "municupalityName" : "Renkum"
}