{
  "regionCode" : "GM0228",
  "numbersDate" : "2021-10-26T02:00:00+02:00",
  "positiveCases" : {
    "new" : 61,
    "trend" : 9,
    "total" : 15255,
    "per100KInhabitants" : 52.063331604003906
  },
  "deaths" : {
    "new" : 0,
    "trend" : -2,
    "total" : 99,
    "per100KInhabitants" : 0
  },
  "securityRegionName" : "Gelderland-Midden",
  "updatedAt" : "2021-10-26T16:31:32+02:00",
  "hospitalAdmissions" : {
    "new" : 0,
    "trend" : 0,
    "total" : 438,
    "per100KInhabitants" : 0
  },
  "provinceName" : "Gelderland",
  "municupalityName" : "Ede"
}