{
  "regionCode" : "GM0228",
  "numbersDate" : "2022-11-04T01:00:00+01:00",
  "positiveCases" : {
    "new" : 15,
    "trend" : 1,
    "total" : 45704,
    "per100KInhabitants" : 12.802457809448242
  },
  "deaths" : {
    "new" : 0,
    "trend" : 0,
    "total" : 40,
    "per100KInhabitants" : 0
  },
  "securityRegionName" : "Gelderland-Midden",
  "updatedAt" : "2022-11-07T15:26:52+01:00",
  "hospitalAdmissions" : {
    "new" : 1,
    "trend" : 1,
    "total" : 236,
    "per100KInhabitants" : 0.8534972071647644
  },
  "provinceName" : "Gelderland",
  "municupalityName" : "Ede"
}