{
  "regionCode" : "GM0281",
  "numbersDate" : "2022-03-02T01:00:00+01:00",
  "positiveCases" : {
    "new" : 92,
    "trend" : 17,
    "total" : 15654,
    "per100KInhabitants" : 218.22149658203125
  },
  "deaths" : {
    "new" : 0,
    "trend" : 0,
    "total" : 81,
    "per100KInhabitants" : 0
  },
  "securityRegionName" : "Gelderland-Zuid",
  "updatedAt" : "2022-03-02T21:24:37+01:00",
  "hospitalAdmissions" : {
    "new" : 1,
    "trend" : 0,
    "total" : 329,
    "per100KInhabitants" : 2.3719727993011475
  },
  "provinceName" : "Gelderland",
  "municupalityName" : "Tiel"
}