{
  "regionCode" : "GM0296",
  "numbersDate" : "2022-01-01T01:00:00+01:00",
  "positiveCases" : {
    "new" : 23,
    "trend" : -8,
    "total" : 7081,
    "per100KInhabitants" : 55.947456359863281
  },
  "deaths" : {
    "new" : 0,
    "trend" : 0,
    "total" : 69,
    "per100KInhabitants" : 0
  },
  "securityRegionName" : "Gelderland-Zuid",
  "updatedAt" : "2022-01-01T17:49:55+01:00",
  "hospitalAdmissions" : {
    "new" : 0,
    "trend" : 0,
    "total" : 221,
    "per100KInhabitants" : 0
  },
  "provinceName" : "Gelderland",
  "municupalityName" : "Wijchen"
}