{
  "regionCode" : "GM0200",
  "numbersDate" : "2021-09-02T00:00:00+02:00",
  "positiveCases" : {
    "new" : 19,
    "trend" : 0,
    "total" : 15136,
    "per100KInhabitants" : 11.598237037658691
  },
  "deaths" : {
    "new" : 0,
    "trend" : 0,
    "total" : 154,
    "per100KInhabitants" : 0
  },
  "securityRegionName" : "Noord- en Oost-Gelderland",
  "updatedAt" : "2021-09-03T11:59:05+02:00",
  "hospitalAdmissions" : {
    "new" : 0,
    "trend" : -2,
    "total" : 526,
    "per100KInhabitants" : 0
  },
  "provinceName" : "Gelderland",
  "municupalityName" : "Apeldoorn"
}