{
  "regionCode" : "GM0353",
  "numbersDate" : "2022-04-26T02:00:00+02:00",
  "positiveCases" : {
    "new" : 5,
    "trend" : -2,
    "total" : 16571,
    "per100KInhabitants" : 14.65888786315918
  },
  "deaths" : {
    "new" : 0,
    "trend" : 0,
    "total" : 60,
    "per100KInhabitants" : 0
  },
  "securityRegionName" : "Utrecht",
  "updatedAt" : "2022-04-26T22:22:39+02:00",
  "hospitalAdmissions" : {
    "new" : 1,
    "trend" : 1,
    "total" : 215,
    "per100KInhabitants" : 2.9317774772644043
  },
  "provinceName" : "Utrecht",
  "municupalityName" : "IJsselstein"
}