{
  "regionCode" : "GM0351",
  "numbersDate" : "2022-03-10T01:00:00+01:00",
  "positiveCases" : {
    "new" : 57,
    "trend" : 15,
    "total" : 6242,
    "per100KInhabitants" : 426.58285522460938
  },
  "deaths" : {
    "new" : 0,
    "trend" : 0,
    "total" : 9,
    "per100KInhabitants" : 0
  },
  "securityRegionName" : "Utrecht",
  "updatedAt" : "2022-03-10T15:21:25+01:00",
  "hospitalAdmissions" : {
    "new" : 0,
    "trend" : 0,
    "total" : 68,
    "per100KInhabitants" : 0
  },
  "provinceName" : "Utrecht",
  "municupalityName" : "Woudenberg"
}