{
  "regionCode" : "GM0308",
  "numbersDate" : "2022-03-09T01:00:00+01:00",
  "positiveCases" : {
    "new" : 74,
    "trend" : 7,
    "total" : 9576,
    "per100KInhabitants" : 297.57119750976562
  },
  "deaths" : {
    "new" : 0,
    "trend" : 0,
    "total" : 30,
    "per100KInhabitants" : 0
  },
  "securityRegionName" : "Utrecht",
  "updatedAt" : "2022-03-09T21:22:12+01:00",
  "hospitalAdmissions" : {
    "new" : 1,
    "trend" : 1,
    "total" : 93,
    "per100KInhabitants" : 4.0212321281433105
  },
  "provinceName" : "Utrecht",
  "municupalityName" : "Baarn"
}