{
  "regionCode" : "GM0376",
  "numbersDate" : "2022-04-05T02:00:00+02:00",
  "positiveCases" : {
    "new" : 6,
    "trend" : -9,
    "total" : 5113,
    "per100KInhabitants" : 51.993068695068359
  },
  "deaths" : {
    "new" : 0,
    "trend" : 0,
    "total" : 8,
    "per100KInhabitants" : 0
  },
  "securityRegionName" : "Gooi en Vechtstreek",
  "updatedAt" : "2022-04-05T15:25:40+02:00",
  "hospitalAdmissions" : {
    "new" : 0,
    "trend" : 0,
    "total" : 45,
    "per100KInhabitants" : 0
  },
  "provinceName" : "Noord-Holland",
  "municupalityName" : "Blaricum"
}