{
  "regionCode" : "GM0484",
  "numbersDate" : "2022-03-26T01:00:00+01:00",
  "positiveCases" : {
    "new" : 186,
    "trend" : -69,
    "total" : 49037,
    "per100KInhabitants" : 166.22428894042969
  },
  "deaths" : {
    "new" : 0,
    "trend" : 0,
    "total" : 153,
    "per100KInhabitants" : 0
  },
  "securityRegionName" : "Hollands-Midden",
  "updatedAt" : "2022-03-26T15:21:05+01:00",
  "hospitalAdmissions" : {
    "new" : 1,
    "trend" : 0,
    "total" : 554,
    "per100KInhabitants" : 0.89367902278900146
  },
  "provinceName" : "Zuid-Holland",
  "municupalityName" : "Alphen aan den Rijn"
}