{
  "regionCode" : "GM0479",
  "numbersDate" : "2021-12-02T01:00:00+01:00",
  "positiveCases" : {
    "new" : 171,
    "trend" : 6,
    "total" : 24405,
    "per100KInhabitants" : 109.06029510498047
  },
  "deaths" : {
    "new" : 0,
    "trend" : 0,
    "total" : 186,
    "per100KInhabitants" : 0
  },
  "securityRegionName" : "Zaanstreek-Waterland",
  "updatedAt" : "2021-12-02T15:31:53+01:00",
  "hospitalAdmissions" : {
    "new" : 2,
    "trend" : -1,
    "total" : 814,
    "per100KInhabitants" : 1.2755590677261353
  },
  "provinceName" : "Noord-Holland",
  "municupalityName" : "Zaanstad"
}