{
  "regionCode" : "GM0484",
  "numbersDate" : "2021-02-16T01:00:00+01:00",
  "positiveCases" : {
    "new" : 24,
    "trend" : 9,
    "total" : 7366,
    "per100KInhabitants" : 21.448295593261719
  },
  "deaths" : {
    "new" : 1,
    "trend" : 0,
    "total" : 97,
    "per100KInhabitants" : 0.89367902278900146
  },
  "securityRegionName" : "Hollands-Midden",
  "updatedAt" : "2021-02-16T15:28:16+01:00",
  "hospitalAdmissions" : {
    "new" : 0,
    "trend" : -1,
    "total" : 270,
    "per100KInhabitants" : 0
  },
  "provinceName" : "Zuid-Holland",
  "municupalityName" : "Alphen aan den Rijn"
}