{
  "regionCode" : "GM0402",
  "numbersDate" : "2022-01-07T01:00:00+01:00",
  "positiveCases" : {
    "new" : 131,
    "trend" : 31,
    "total" : 15085,
    "per100KInhabitants" : 144.22389221191406
  },
  "deaths" : {
    "new" : 0,
    "trend" : 0,
    "total" : 106,
    "per100KInhabitants" : 0
  },
  "securityRegionName" : "Gooi en Vechtstreek",
  "updatedAt" : "2022-01-07T17:56:02+01:00",
  "hospitalAdmissions" : {
    "new" : 0,
    "trend" : -1,
    "total" : 229,
    "per100KInhabitants" : 0
  },
  "provinceName" : "Noord-Holland",
  "municupalityName" : "Hilversum"
}