{
  "regionCode" : "GM0405",
  "numbersDate" : "2022-03-17T01:00:00+01:00",
  "positiveCases" : {
    "new" : 206,
    "trend" : -27,
    "total" : 31426,
    "per100KInhabitants" : 281.18646240234375
  },
  "deaths" : {
    "new" : 0,
    "trend" : 0,
    "total" : 59,
    "per100KInhabitants" : 0
  },
  "securityRegionName" : "Noord-Holland-Noord",
  "updatedAt" : "2022-03-17T21:21:59+01:00",
  "hospitalAdmissions" : {
    "new" : 2,
    "trend" : 2,
    "total" : 458,
    "per100KInhabitants" : 2.7299654483795166
  },
  "provinceName" : "Noord-Holland",
  "municupalityName" : "Hoorn"
}