{
  "regionCode" : "GM0498",
  "numbersDate" : "2021-11-13T01:00:00+01:00",
  "positiveCases" : {
    "new" : 19,
    "trend" : 11,
    "total" : 2629,
    "per100KInhabitants" : 96.353775024414062
  },
  "deaths" : {
    "new" : 0,
    "trend" : 0,
    "total" : 13,
    "per100KInhabitants" : 0
  },
  "securityRegionName" : "Noord-Holland-Noord",
  "updatedAt" : "2021-11-13T17:46:33+01:00",
  "hospitalAdmissions" : {
    "new" : 0,
    "trend" : 0,
    "total" : 65,
    "per100KInhabitants" : 0
  },
  "provinceName" : "Noord-Holland",
  "municupalityName" : "Drechterland"
}