{
  "regionCode" : "GM0537",
  "numbersDate" : "2022-03-26T01:00:00+01:00",
  "positiveCases" : {
    "new" : 70,
    "trend" : -42,
    "total" : 31882,
    "per100KInhabitants" : 106.45901489257812
  },
  "deaths" : {
    "new" : 0,
    "trend" : 0,
    "total" : 71,
    "per100KInhabitants" : 0
  },
  "securityRegionName" : "Hollands-Midden",
  "updatedAt" : "2022-03-26T19:22:27+01:00",
  "hospitalAdmissions" : {
    "new" : 0,
    "trend" : -1,
    "total" : 366,
    "per100KInhabitants" : 0
  },
  "provinceName" : "Zuid-Holland",
  "municupalityName" : "Katwijk"
}