{
  "regionCode" : "GM0597",
  "numbersDate" : "2021-08-26T02:00:00+02:00",
  "positiveCases" : {
    "new" : 3,
    "trend" : -8,
    "total" : 6530,
    "per100KInhabitants" : 6.4950532913208008
  },
  "deaths" : {
    "new" : 0,
    "trend" : 0,
    "total" : 90,
    "per100KInhabitants" : 0
  },
  "securityRegionName" : "Rotterdam-Rijnmond",
  "updatedAt" : "2021-08-26T15:31:04+02:00",
  "hospitalAdmissions" : {
    "new" : 0,
    "trend" : 0,
    "total" : 305,
    "per100KInhabitants" : 0
  },
  "provinceName" : "Zuid-Holland",
  "municupalityName" : "Ridderkerk"
}