{
  "regionCode" : "GM0523",
  "numbersDate" : "2022-02-16T01:00:00+01:00",
  "positiveCases" : {
    "new" : 80,
    "trend" : 33,
    "total" : 8018,
    "per100KInhabitants" : 437.27792358398438
  },
  "deaths" : {
    "new" : 0,
    "trend" : 0,
    "total" : 32,
    "per100KInhabitants" : 0
  },
  "securityRegionName" : "Zuid-Holland-Zuid",
  "updatedAt" : "2022-02-16T15:26:40+01:00",
  "hospitalAdmissions" : {
    "new" : 0,
    "trend" : 0,
    "total" : 105,
    "per100KInhabitants" : 0
  },
  "provinceName" : "Zuid-Holland",
  "municupalityName" : "Hardinxveld-Giessendam"
}