{
  "regionCode" : "GM0542",
  "numbersDate" : "2022-03-03T01:00:00+01:00",
  "positiveCases" : {
    "new" : 59,
    "trend" : 15,
    "total" : 11307,
    "per100KInhabitants" : 199.82386779785156
  },
  "deaths" : {
    "new" : 0,
    "trend" : 0,
    "total" : 78,
    "per100KInhabitants" : 0
  },
  "securityRegionName" : "Rotterdam-Rijnmond",
  "updatedAt" : "2022-03-03T15:24:07+01:00",
  "hospitalAdmissions" : {
    "new" : 0,
    "trend" : 0,
    "total" : 216,
    "per100KInhabitants" : 0
  },
  "provinceName" : "Zuid-Holland",
  "municupalityName" : "Krimpen aan den IJssel"
}