{
  "regionCode" : "GM0501",
  "numbersDate" : "2022-03-07T01:00:00+01:00",
  "positiveCases" : {
    "new" : 31,
    "trend" : -4,
    "total" : 5963,
    "per100KInhabitants" : 179.49163818359375
  },
  "deaths" : {
    "new" : 0,
    "trend" : 0,
    "total" : 13,
    "per100KInhabitants" : 0
  },
  "securityRegionName" : "Rotterdam-Rijnmond",
  "updatedAt" : "2022-03-07T17:23:19+01:00",
  "hospitalAdmissions" : {
    "new" : 0,
    "trend" : 0,
    "total" : 100,
    "per100KInhabitants" : 0
  },
  "provinceName" : "Zuid-Holland",
  "municupalityName" : "Brielle"
}