{
  "regionCode" : "GM0512",
  "numbersDate" : "2022-02-01T01:00:00+01:00",
  "positiveCases" : {
    "new" : 205,
    "trend" : 100,
    "total" : 10730,
    "per100KInhabitants" : 553.72479248046875
  },
  "deaths" : {
    "new" : 0,
    "trend" : 0,
    "total" : 48,
    "per100KInhabitants" : 0
  },
  "securityRegionName" : "Zuid-Holland-Zuid",
  "updatedAt" : "2022-02-01T21:30:33+01:00",
  "hospitalAdmissions" : {
    "new" : 0,
    "trend" : 0,
    "total" : 189,
    "per100KInhabitants" : 0
  },
  "provinceName" : "Zuid-Holland",
  "municupalityName" : "Gorinchem"
}