{
  "regionCode" : "GM0579",
  "numbersDate" : "2022-02-04T01:00:00+01:00",
  "positiveCases" : {
    "new" : 37,
    "trend" : -128,
    "total" : 6303,
    "per100KInhabitants" : 148.95329284667969
  },
  "deaths" : {
    "new" : 0,
    "trend" : 0,
    "total" : 32,
    "per100KInhabitants" : 0
  },
  "securityRegionName" : "Hollands-Midden",
  "updatedAt" : "2022-02-04T15:22:21+01:00",
  "hospitalAdmissions" : {
    "new" : 0,
    "trend" : 0,
    "total" : 82,
    "per100KInhabitants" : 0
  },
  "provinceName" : "Zuid-Holland",
  "municupalityName" : "Oegstgeest"
}