{
  "regionCode" : "GM0589",
  "numbersDate" : "2021-03-12T01:00:00+01:00",
  "positiveCases" : {
    "new" : 5,
    "trend" : 0,
    "total" : 724,
    "per100KInhabitants" : 48.8758544921875
  },
  "deaths" : {
    "new" : 0,
    "trend" : 0,
    "total" : 12,
    "per100KInhabitants" : 0
  },
  "securityRegionName" : "Utrecht",
  "updatedAt" : "2021-03-12T21:32:14+01:00",
  "hospitalAdmissions" : {
    "new" : 0,
    "trend" : 0,
    "total" : 41,
    "per100KInhabitants" : 0
  },
  "provinceName" : "Utrecht",
  "municupalityName" : "Oudewater"
}