{
  "regionCode" : "GM0553",
  "numbersDate" : "2022-07-22T02:00:00+02:00",
  "positiveCases" : {
    "new" : 3,
    "trend" : -5,
    "total" : 10647,
    "per100KInhabitants" : 13.069046974182129
  },
  "deaths" : {
    "new" : 0,
    "trend" : 0,
    "total" : 24,
    "per100KInhabitants" : 0
  },
  "securityRegionName" : "Hollands-Midden",
  "updatedAt" : "2022-07-22T20:23:14+02:00",
  "hospitalAdmissions" : {
    "new" : 0,
    "trend" : 0,
    "total" : 102,
    "per100KInhabitants" : 0
  },
  "provinceName" : "Zuid-Holland",
  "municupalityName" : "Lisse"
}