{
  "regionCode" : "GM0654",
  "numbersDate" : "2021-02-06T01:00:00+01:00",
  "positiveCases" : {
    "new" : 4,
    "trend" : 2,
    "total" : 791,
    "per100KInhabitants" : 17.590923309326172
  },
  "deaths" : {
    "new" : 0,
    "trend" : 0,
    "total" : 5,
    "per100KInhabitants" : 0
  },
  "securityRegionName" : "Zeeland",
  "updatedAt" : "2021-02-06T15:27:11+01:00",
  "hospitalAdmissions" : {
    "new" : 0,
    "trend" : 0,
    "total" : 25,
    "per100KInhabitants" : 0
  },
  "provinceName" : "Zeeland",
  "municupalityName" : "Borsele"
}