{
  "regionCode" : "GM0642",
  "numbersDate" : "2021-03-22T01:00:00+01:00",
  "positiveCases" : {
    "new" : 26,
    "trend" : 9,
    "total" : 3907,
    "per100KInhabitants" : 58.117439270019531
  },
  "deaths" : {
    "new" : 0,
    "trend" : 0,
    "total" : 87,
    "per100KInhabitants" : 0
  },
  "securityRegionName" : "Zuid-Holland-Zuid",
  "updatedAt" : "2021-03-22T19:02:25+01:00",
  "hospitalAdmissions" : {
    "new" : 0,
    "trend" : -1,
    "total" : 231,
    "per100KInhabitants" : 0
  },
  "provinceName" : "Zuid-Holland",
  "municupalityName" : "Zwijndrecht"
}