{
  "regionCode" : "GM0603",
  "numbersDate" : "2021-11-11T01:00:00+01:00",
  "positiveCases" : {
    "new" : 35,
    "trend" : 3,
    "total" : 6687,
    "per100KInhabitants" : 64.279159545898438
  },
  "deaths" : {
    "new" : 0,
    "trend" : 0,
    "total" : 77,
    "per100KInhabitants" : 0
  },
  "securityRegionName" : "Haaglanden",
  "updatedAt" : "2021-11-11T15:31:24+01:00",
  "hospitalAdmissions" : {
    "new" : 1,
    "trend" : -1,
    "total" : 264,
    "per100KInhabitants" : 1.8365473747253418
  },
  "provinceName" : "Zuid-Holland",
  "municupalityName" : "Rijswijk"
}