{
  "regionCode" : "GM0777",
  "numbersDate" : "2022-01-29T01:00:00+01:00",
  "positiveCases" : {
    "new" : 279,
    "trend" : -17,
    "total" : 10165,
    "per100KInhabitants" : 635.85394287109375
  },
  "deaths" : {
    "new" : 0,
    "trend" : 0,
    "total" : 40,
    "per100KInhabitants" : 0
  },
  "securityRegionName" : "Midden- en West-Brabant",
  "updatedAt" : "2022-01-29T21:31:22+01:00",
  "hospitalAdmissions" : {
    "new" : 0,
    "trend" : -1,
    "total" : 217,
    "per100KInhabitants" : 0
  },
  "provinceName" : "Noord-Brabant",
  "municupalityName" : "Etten-Leur"
}