{
  "regionCode" : "GM0756",
  "numbersDate" : "2021-04-30T02:00:00+02:00",
  "positiveCases" : {
    "new" : 22,
    "trend" : 7,
    "total" : 2995,
    "per100KInhabitants" : 74.919120788574219
  },
  "deaths" : {
    "new" : 1,
    "trend" : 1,
    "total" : 44,
    "per100KInhabitants" : 3.4054145812988281
  },
  "securityRegionName" : "Brabant-Noord",
  "updatedAt" : "2021-04-30T21:30:08+02:00",
  "hospitalAdmissions" : {
    "new" : 0,
    "trend" : 0,
    "total" : 120,
    "per100KInhabitants" : 0
  },
  "provinceName" : "Noord-Brabant",
  "municupalityName" : "Boxmeer"
}