{
  "regionCode" : "GM0888",
  "numbersDate" : "2022-03-14T01:00:00+01:00",
  "positiveCases" : {
    "new" : 53,
    "trend" : -27,
    "total" : 6873,
    "per100KInhabitants" : 334.0687255859375
  },
  "deaths" : {
    "new" : 0,
    "trend" : 0,
    "total" : 16,
    "per100KInhabitants" : 0
  },
  "securityRegionName" : "Limburg-Zuid",
  "updatedAt" : "2022-03-14T21:22:14+01:00",
  "hospitalAdmissions" : {
    "new" : 0,
    "trend" : 0,
    "total" : 81,
    "per100KInhabitants" : 0
  },
  "provinceName" : "Limburg",
  "municupalityName" : "Beek"
}