{
  "regionCode" : "GM0995",
  "numbersDate" : "2022-01-26T01:00:00+01:00",
  "positiveCases" : {
    "new" : 94,
    "trend" : -101,
    "total" : 16686,
    "per100KInhabitants" : 119.59591674804688
  },
  "deaths" : {
    "new" : 0,
    "trend" : 0,
    "total" : 83,
    "per100KInhabitants" : 0
  },
  "securityRegionName" : "Flevoland",
  "updatedAt" : "2022-01-26T17:49:35+01:00",
  "hospitalAdmissions" : {
    "new" : 4,
    "trend" : 0,
    "total" : 487,
    "per100KInhabitants" : 5.0891880989074707
  },
  "provinceName" : "Flevoland",
  "municupalityName" : "Lelystad"
}