{
  "regionCode" : "GM1641",
  "numbersDate" : "2022-03-16T01:00:00+01:00",
  "positiveCases" : {
    "new" : 72,
    "trend" : -2,
    "total" : 9916,
    "per100KInhabitants" : 300.43814086914062
  },
  "deaths" : {
    "new" : 0,
    "trend" : 0,
    "total" : 45,
    "per100KInhabitants" : 0
  },
  "securityRegionName" : "Limburg-Noord",
  "updatedAt" : "2022-03-16T15:21:52+01:00",
  "hospitalAdmissions" : {
    "new" : 0,
    "trend" : 0,
    "total" : 182,
    "per100KInhabitants" : 0
  },
  "provinceName" : "Limburg",
  "municupalityName" : "Maasgouw"
}