{
  "regionCode" : "GM1680",
  "numbersDate" : "2021-02-24T01:00:00+01:00",
  "positiveCases" : {
    "new" : 3,
    "trend" : 1,
    "total" : 932,
    "per100KInhabitants" : 11.790135383605957
  },
  "deaths" : {
    "new" : 0,
    "trend" : 0,
    "total" : 15,
    "per100KInhabitants" : 0
  },
  "securityRegionName" : "Drenthe",
  "updatedAt" : "2021-02-24T23:30:00+01:00",
  "hospitalAdmissions" : {
    "new" : 0,
    "trend" : 0,
    "total" : 15,
    "per100KInhabitants" : 0
  },
  "provinceName" : "Drenthe",
  "municupalityName" : "Aa en Hunze"
}