{
  "regionCode" : "GM1652",
  "numbersDate" : "2022-02-21T01:00:00+01:00",
  "positiveCases" : {
    "new" : 67,
    "trend" : 1,
    "total" : 10510,
    "per100KInhabitants" : 218.07765197753906
  },
  "deaths" : {
    "new" : 0,
    "trend" : 0,
    "total" : 44,
    "per100KInhabitants" : 0
  },
  "securityRegionName" : "Brabant-Zuidoost",
  "updatedAt" : "2022-02-21T15:22:01+01:00",
  "hospitalAdmissions" : {
    "new" : 0,
    "trend" : 0,
    "total" : 215,
    "per100KInhabitants" : 0
  },
  "provinceName" : "Noord-Brabant",
  "municupalityName" : "Gemert-Bakel"
}