{
  "regionCode" : "GM1931",
  "numbersDate" : "2021-02-16T01:00:00+01:00",
  "positiveCases" : {
    "new" : 16,
    "trend" : 5,
    "total" : 3888,
    "per100KInhabitants" : 28.409595489501953
  },
  "deaths" : {
    "new" : 1,
    "trend" : 1,
    "total" : 60,
    "per100KInhabitants" : 1.7755997180938721
  },
  "securityRegionName" : "Hollands-Midden",
  "updatedAt" : "2021-02-16T16:28:16+01:00",
  "hospitalAdmissions" : {
    "new" : 0,
    "trend" : -2,
    "total" : 180,
    "per100KInhabitants" : 0
  },
  "provinceName" : "Zuid-Holland",
  "municupalityName" : "Krimpenerwaard"
}