{
  "hospitalOccupancy" : {
    "newAdmissionsTrend" : 142,
    "currentlyOccupiedTrend" : 2,
    "currentlyOccupied" : 1477,
    "newAdmissionsPer100KInhabitants" : 2.4299755096435547,
    "newAdmissions" : 423,
    "currentlyOccupiedPer100KInhabitants" : 8.4848079681396484
  },
  "numbersDate" : "2022-02-16T01:00:00+01:00",
  "positiveCases" : {
    "new" : 63779,
    "trend" : 10257,
    "percentageOfPopulation" : 0.98000001907348633,
    "total" : 5906860,
    "per100KInhabitants" : 366.38629150390625
  },
  "intensiveCareOccupancy" : {
    "newAdmissionsTrend" : 0,
    "currentlyOccupiedTrend" : -8,
    "currentlyOccupied" : 173,
    "newAdmissionsPer100KInhabitants" : 0.13787093758583069,
    "newAdmissions" : 24,
    "currentlyOccupiedPer100KInhabitants" : 0.9938197135925293
  },
  "homeAdmissions" : {
    "newAdmissionsTrend" : -6,
    "currentlyOccupiedTrend" : -10,
    "currentlyOccupied" : 86,
    "newAdmissionsPer100KInhabitants" : 0.011489245109260082,
    "newAdmissions" : 2,
    "currentlyOccupiedPer100KInhabitants" : 0.49403750896453857
  },
  "deaths" : {
    "new" : 18,
    "trend" : 6,
    "total" : 21432,
    "per100KInhabitants" : 0.10340320318937302
  },
  "hospitalAdmissions" : {
    "new" : 423,
    "trend" : 142,
    "total" : 95540,
    "per100KInhabitants" : 2.4299755096435547
  },
  "updatedAt" : "2022-02-16T17:42:48+01:00",
  "vaccinations" : {
    "trend" : 229338,
    "lastUpdated" : "2021-12-19T01:00:00+01:00",
    "numbers" : {
      "new" : 1390349,
      "average" : 282262,
      "trend" : 229338,
      "percentageOfPopulation" : 0.7009468674659729,
      "total" : 26573190
    },
    "average" : 282262,
    "herdImmunityEstimatedDate" : "2022-02-16T17:42:48+01:00",
    "percentageOfPopulation" : 0.7009468674659729,
    "total" : 26573190,
    "herdImmunityCurrentTrendDate" : "2022-02-16T17:42:48+01:00",
    "new" : 1390349
  },
  "regionCode" : "NL00"
}