{
  "deaths" : {
    "new" : 0,
    "trend" : 0,
    "total" : 106,
    "per100KInhabitants" : 0
  },
  "numbersDate" : "2022-11-15T01:00:00+01:00",
  "positiveCases" : {
    "new" : 24,
    "trend" : 14,
    "total" : 212339,
    "per100KInhabitants" : 4.0964999198913574
  },
  "hospitalAdmissions" : {
    "new" : 2,
    "trend" : 2,
    "total" : 1440,
    "per100KInhabitants" : 0.34137499332427979
  },
  "updatedAt" : "2022-11-15T15:24:26+01:00",
  "provinceName" : "Groningen",
  "regionCode" : "PV20"
}