{
  "deaths" : {
    "new" : 1,
    "trend" : 0,
    "total" : 1491,
    "per100KInhabitants" : 0.073809780180454254
  },
  "numbersDate" : "2022-02-11T01:00:00+01:00",
  "positiveCases" : {
    "new" : 6870,
    "trend" : -462,
    "total" : 458813,
    "per100KInhabitants" : 507.07321166992188
  },
  "hospitalAdmissions" : {
    "new" : 20,
    "trend" : 5,
    "total" : 6523,
    "per100KInhabitants" : 1.4761955738067627
  },
  "updatedAt" : "2022-02-11T15:25:28+01:00",
  "provinceName" : "Utrecht",
  "regionCode" : "PV26"
}