{
  "deaths" : {
    "new" : 0,
    "trend" : 0,
    "total" : 3713,
    "per100KInhabitants" : 0
  },
  "numbersDate" : "2022-07-14T02:00:00+02:00",
  "positiveCases" : {
    "new" : 950,
    "trend" : 22,
    "total" : 1257311,
    "per100KInhabitants" : 37.06658935546875
  },
  "hospitalAdmissions" : {
    "new" : 10,
    "trend" : 3,
    "total" : 19024,
    "per100KInhabitants" : 0.39017462730407715
  },
  "updatedAt" : "2022-07-14T15:29:25+02:00",
  "provinceName" : "Noord-Brabant",
  "regionCode" : "PV30"
}