{
  "deaths" : {
    "new" : 0,
    "trend" : 0,
    "total" : 451,
    "per100KInhabitants" : 0
  },
  "numbersDate" : "2022-05-20T02:00:00+02:00",
  "positiveCases" : {
    "new" : 30,
    "trend" : -6,
    "total" : 202472,
    "per100KInhabitants" : 6.0767865180969238
  },
  "securityRegionName" : "Drenthe",
  "updatedAt" : "2022-05-20T16:22:24+02:00",
  "hospitalAdmissions" : {
    "new" : 8,
    "trend" : 8,
    "total" : 2292,
    "per100KInhabitants" : 1.6204763650894165
  },
  "provinceName" : "Drenthe",
  "regionCode" : "VR03"
}