{
  "deaths" : {
    "new" : 1,
    "trend" : 0,
    "total" : 810,
    "per100KInhabitants" : 0.15846253931522369
  },
  "numbersDate" : "2022-03-05T01:00:00+01:00",
  "positiveCases" : {
    "new" : 2096,
    "trend" : -93,
    "total" : 251748,
    "per100KInhabitants" : 332.13748168945312
  },
  "securityRegionName" : "Twente",
  "updatedAt" : "2022-03-05T15:21:23+01:00",
  "hospitalAdmissions" : {
    "new" : 10,
    "trend" : 7,
    "total" : 3697,
    "per100KInhabitants" : 1.5846253633499146
  },
  "provinceName" : "Overijssel",
  "regionCode" : "VR05"
}