{
  "deaths" : {
    "new" : 10,
    "trend" : 10,
    "total" : 950,
    "per100KInhabitants" : 1.2081218957901001
  },
  "numbersDate" : "2021-12-14T01:00:00+01:00",
  "positiveCases" : {
    "new" : 721,
    "trend" : 100,
    "total" : 125132,
    "per100KInhabitants" : 87.1055908203125
  },
  "securityRegionName" : "Noord- en Oost-Gelderland",
  "updatedAt" : "2021-12-14T15:29:04+01:00",
  "hospitalAdmissions" : {
    "new" : 25,
    "trend" : 23,
    "total" : 3502,
    "per100KInhabitants" : 3.0203049182891846
  },
  "provinceName" : "Gelderland",
  "regionCode" : "VR06"
}