{
  "deaths" : {
    "new" : 0,
    "trend" : 0,
    "total" : 1506,
    "per100KInhabitants" : 0
  },
  "numbersDate" : "2022-03-03T01:00:00+01:00",
  "positiveCases" : {
    "new" : 4663,
    "trend" : 331,
    "total" : 540467,
    "per100KInhabitants" : 344.17501831054688
  },
  "securityRegionName" : "Utrecht",
  "updatedAt" : "2022-03-03T17:23:30+01:00",
  "hospitalAdmissions" : {
    "new" : 12,
    "trend" : -12,
    "total" : 6816,
    "per100KInhabitants" : 0.88571733236312866
  },
  "provinceName" : "Utrecht",
  "regionCode" : "VR09"
}