{
  "deaths" : {
    "new" : 1,
    "trend" : 1,
    "total" : 1482,
    "per100KInhabitants" : 0.073809780180454254
  },
  "numbersDate" : "2022-01-19T01:00:00+01:00",
  "positiveCases" : {
    "new" : 2394,
    "trend" : -506,
    "total" : 294289,
    "per100KInhabitants" : 176.70060729980469
  },
  "securityRegionName" : "Utrecht",
  "updatedAt" : "2022-01-19T17:50:31+01:00",
  "hospitalAdmissions" : {
    "new" : 7,
    "trend" : -11,
    "total" : 6192,
    "per100KInhabitants" : 0.51666849851608276
  },
  "provinceName" : "Utrecht",
  "regionCode" : "VR09"
}