{
  "deaths" : {
    "new" : 0,
    "trend" : 0,
    "total" : 297,
    "per100KInhabitants" : 0
  },
  "numbersDate" : "2022-01-07T01:00:00+01:00",
  "positiveCases" : {
    "new" : 471,
    "trend" : 135,
    "total" : 46586,
    "per100KInhabitants" : 183.21501159667969
  },
  "securityRegionName" : "Gooi en Vechtstreek",
  "updatedAt" : "2022-01-07T21:36:32+01:00",
  "hospitalAdmissions" : {
    "new" : 2,
    "trend" : -1,
    "total" : 726,
    "per100KInhabitants" : 0.77798306941986084
  },
  "provinceName" : "Noord-Holland",
  "regionCode" : "VR14"
}