{
  "deaths" : {
    "new" : 1,
    "trend" : -1,
    "total" : 1689,
    "per100KInhabitants" : 0.075561001896858215
  },
  "numbersDate" : "2021-03-13T01:00:00+01:00",
  "positiveCases" : {
    "new" : 672,
    "trend" : 177,
    "total" : 103695,
    "per100KInhabitants" : 50.776992797851562
  },
  "securityRegionName" : "Rotterdam-Rijnmond",
  "updatedAt" : "2021-03-13T17:51:03+01:00",
  "hospitalAdmissions" : {
    "new" : 10,
    "trend" : -7,
    "total" : 5190,
    "per100KInhabitants" : 0.75560998916625977
  },
  "provinceName" : "Zuid-Holland",
  "regionCode" : "VR17"
}