{
  "deaths" : {
    "new" : 1,
    "trend" : 0,
    "total" : 1312,
    "per100KInhabitants" : 0.089358560740947723
  },
  "numbersDate" : "2022-03-11T01:00:00+01:00",
  "positiveCases" : {
    "new" : 5879,
    "trend" : 342,
    "total" : 480342,
    "per100KInhabitants" : 525.33892822265625
  },
  "securityRegionName" : "Midden- en West-Brabant",
  "updatedAt" : "2022-03-11T17:23:58+01:00",
  "hospitalAdmissions" : {
    "new" : 21,
    "trend" : -1,
    "total" : 7186,
    "per100KInhabitants" : 1.8765296936035156
  },
  "provinceName" : "Noord-Brabant",
  "regionCode" : "VR20"
}