{
  "deaths" : {
    "new" : 0,
    "trend" : 0,
    "total" : 249,
    "per100KInhabitants" : 0
  },
  "numbersDate" : "2021-08-22T02:00:00+02:00",
  "positiveCases" : {
    "new" : 106,
    "trend" : 1,
    "total" : 42006,
    "per100KInhabitants" : 25.057857513427734
  },
  "securityRegionName" : "Flevoland",
  "updatedAt" : "2021-08-22T15:30:09+02:00",
  "hospitalAdmissions" : {
    "new" : 2,
    "trend" : -1,
    "total" : 1169,
    "per100KInhabitants" : 0.47278976440429688
  },
  "provinceName" : "Flevoland",
  "regionCode" : "VR25"
}